Workbook

Sheet APP
B2: SIMULADOR DE INVESTIMENTOS
B9: CONFIGURAÇÕES
B10: Salário | D10: 2000
B11: Rendimento Carteira | D11: 0.006
B12: Sugestão de Investimento (30%) | D12: =B10*0.3
B14: INVESTIMENTO MENSAL
B15: Quanto investir por mês ? | D15: 200
B16: Por Quantos Anos ? | D16: 5
B17: Taxa de Rendimento mensal ? | D17: =D11
B18: Patrimônio acumulado ? | D18: =VF(D17; D16*12; -D15)
B19: Retorno Mensal Estimado ? | D19: =D18*D11
B21: Cenários (Projeção de Longo Prazo)
B22: Anos | C22: Patrimônio Acumulado | D22: Retorno Mensal Estimado
B23: 2 | C23: =VF($D$17; B23*12; -$D$15) | D23: =C23*$D$17
B24: 5 | C24: =VF($D$17; B24*12; -$D$15) | D24: =C24*$D$17
B25: 10 | C25: =VF($D$17; B25*12; -$D$15) | D25: =C25*$D$17
B26: 20 | C26: =VF($D$17; B26*12; -$D$15) | D26: =C26*$D$17
B27: 30 | C27: =VF($D$17; B27*12; -$D$15) | D27: =C27*$D$17
B29: DISTRIBUIÇÃO DE CARTEIRA POR PERFIL
B30: PERFIL SELECIONADO | C30: Moderado
B31: VALOR A SER INVESTIDO POR MÊS | C31: =D15
B33: TIPO DE INVESTIMENTO | C33: Percentual Sugerido | D33: Valores (R$)
B34: RENDA FIXA | C34: =PROCX($C$30 & "-" & B34; Database_Profiles!$A$2:$A$19; Database_Profiles!$D$2:$D$19; 0) | D34: =C34*$C$31
B35: IMOBILIÁRIO | C35: =PROCX($C$30 & "-" & B35; Database_Profiles!$A$2:$A$19; Database_Profiles!$D$2:$D$19; 0) | D35: =C35*$C$31
B36: MULTIMERCADO | C36: =PROCX($C$30 & "-" & B36; Database_Profiles!$A$2:$A$19; Database_Profiles!$D$2:$D$19; 0) | D36: =C36*$C$31
B37: AÇÕES BR | C37: =PROCX($C$30 & "-" & B37; Database_Profiles!$A$2:$A$19; Database_Profiles!$D$2:$D$19; 0) | D37: =C37*$C$31
B38: INTERNACIONAL | C38: =PROCX($C$30 & "-" & B38; Database_Profiles!$A$2:$A$19; Database_Profiles!$D$2:$D$19; 0) | D38: =C38*$C$31
B39: CRIPTOMOEDAS | C39: =PROCX($C$30 & "-" & B39; Database_Profiles!$A$2:$A$19; Database_Profiles!$D$2:$D$19; 0) | D39: =C39*$C$31
B40: TOTAL | C40: =SOMA(C34:C39) | D40: =SOMA(D34:D39)

Sheet Database_Profiles
A1: CHAVE | B1: PERFIL | C1: TIPO DE INVESTIMENTO | D1: %
A2: Conservador-RENDA FIXA | B2: Conservador | C2: RENDA FIXA | D2: 0.5
A3: Conservador-IMOBILIÁRIO | B3: Conservador | C3: IMOBILIÁRIO | D3: 0.3
A4: Conservador-MULTIMERCADO | B4: Conservador | C4: MULTIMERCADO | D4: 0.1
A5: Conservador-AÇÕES BR | B5: Conservador | C5: AÇÕES BR | D5: 0.1
A6: Conservador-INTERNACIONAL | B6: Conservador | C6: INTERNACIONAL | D6: 0
A7: Conservador-CRIPTOMOEDAS | B7: Conservador | C7: CRIPTOMOEDAS | D7: 0
A8: Moderado-RENDA FIXA | B8: Moderado | C8: RENDA FIXA | D8: 0.35
A9: Moderado-IMOBILIÁRIO | B9: Moderado | C9: IMOBILIÁRIO | D9: 0.32
A10: Moderado-MULTIMERCADO | B10: Moderado | C10: MULTIMERCADO | D10: 0.08
A11: Moderado-AÇÕES BR | B11: Moderado | C11: AÇÕES BR | D11: 0.1
A12: Moderado-INTERNACIONAL | B12: Moderado | C12: INTERNACIONAL | D12: 0.1
A13: Moderado-CRIPTOMOEDAS | B13: Moderado | C13: CRIPTOMOEDAS | D13: 0.05
... A19: Agressivo-CRIPTOMOEDAS | B19: Agressivo | C19: CRIPTOMOEDAS | D19: 0.1
