Workbook

Sheet APP
B2: SIMULADOR DE INVESTIMENTOS MULTICLASSE
B9: 1. CONFIGURAÇÕES GLOBAIS
B10: Salário Base | D10: 2000
B11: Taxa Poupança Sugerida | D11: 0.3
B12: Sugestão de Aporte Mensal (30%) | D12: =D10*D11
B15: 2. SELEÇÃO DE PERFIL E APORTE
B16: Perfil de Investimento | C16: Moderado
B17: Valor Efetivo Aportado por Mês | D17: =D12
B18: Taxa de Retorno Média da Carteira (a.m.) | D18: =SOMAPRODUTO(C24:C29; E24:E29) / 12
B21: 3. DISTRIBUIÇÃO DA CARTEIRA POR ATIVO
B23: TIPO DE INVESTIMENTO | C23: Percentual na Carteira | D23: Aporte Alocado (R$) | E23: Retorno Esperado (a.a.)
B24: RENDA FIXA | C24: =PROCV($C$16 & "-" & B24; Database_Profiles!$A$2:$E$19; 4; FALSO) | D24: =C24*$D$17 | E24: =PROCV($C$16 & "-" & B24; Database_Profiles!$A$2:$E$19; 5; FALSO)
B25: IMOBILIÁRIO | C25: =PROCV($C$16 & "-" & B25; Database_Profiles!$A$2:$E$19; 4; FALSO) | D25: =C25*$D$17 | E25: =PROCV($C$16 & "-" & B25; Database_Profiles!$A$2:$E$19; 5; FALSO)
B26: MULTIMERCADO | C26: =PROCV($C$16 & "-" & B26; Database_Profiles!$A$2:$E$19; 4; FALSO) | D26: =C26*$D$17 | E26: =PROCV($C$16 & "-" & B26; Database_Profiles!$A$2:$E$19; 5; FALSO)
B27: AÇÕES BR | C27: =PROCV($C$16 & "-" & B27; Database_Profiles!$A$2:$E$19; 4; FALSO) | D27: =C27*$D$17 | E27: =PROCV($C$16 & "-" & B27; Database_Profiles!$A$2:$E$19; 5; FALSO)
B28: INTERNACIONAL | C28: =PROCV($C$16 & "-" & B28; Database_Profiles!$A$2:$E$19; 4; FALSO) | D28: =C28*$D$17 | E28: =PROCV($C$16 & "-" & B28; Database_Profiles!$A$2:$E$19; 5; FALSO)
B29: CRIPTOMOEDAS | C29: =PROCV($C$16 & "-" & B29; Database_Profiles!$A$2:$E$19; 4; FALSO) | D29: =C29*$D$17 | E29: =PROCV($C$16 & "-" & B29; Database_Profiles!$A$2:$E$19; 5; FALSO)
B30: TOTAL | C30: =SOMA(C24:C29) | D30: =SOMA(D24:D29)
B32: 4. PROJEÇÕES DE LONGO PRAZO (CENÁRIOS)
B33: Anos | C33: Total Aportado (Capital) | D33: Patrimônio Acumulado (com Juros) | E33: Rendimento Mensal Estimado
B34: 2 | C34: =$D$17*2*12 | D34: =VF($D$18; B34*12; -$D$17) | E34: =D34*$D$18
B35: 5 | C35: =$D$17*5*12 | D35: =VF($D$18; B35*12; -$D$17) | E35: =D35*$D$18
B36: 10 | C36: =$D$17*10*12 | D36: =VF($D$18; B36*12; -$D$17) | E36: =D36*$D$18
B37: 20 | C37: =$D$17*20*12 | D37: =VF($D$18; B37*12; -$D$17) | E37: =D37*$D$18
B38: 30 | C38: =$D$17*30*12 | D38: =VF($D$18; B38*12; -$D$17) | E38: =D38*$D$18

Sheet Database_Profiles
A1: CHAVE | B1: PERFIL | C1: TIPO DE INVESTIMENTO | D1: % | E1: RETORNO AA | F1: Perfis_Unicos
A2: Conservador-RENDA FIXA | B2: Conservador | C2: RENDA FIXA | D2: 0.5 | E2: 0.1 | F2: Conservador
A3: Conservador-IMOBILIÁRIO | B3: Conservador | C3: IMOBILIÁRIO | D3: 0.3 | E3: 0.11 | F3: Moderado
A4: Conservador-MULTIMERCADO | B4: Conservador | C4: MULTIMERCADO | D4: 0.1 | E4: 0.105 | F4: Agressivo
A5: Conservador-AÇÕES BR | B5: Conservador | C5: AÇÕES BR | D5: 0.1 | E5: 0.12
A6: Conservador-INTERNACIONAL | B6: Conservador | C6: INTERNACIONAL | D6: 0 | E6: 0.115
A7: Conservador-CRIPTOMOEDAS | B7: Conservador | C7: CRIPTOMOEDAS | D7: 0 | E7: 0.18
A8: Moderado-RENDA FIXA | B8: Moderado | C8: RENDA FIXA | D8: 0.35 | E8: 0.1
A9: Moderado-IMOBILIÁRIO | B9: Moderado | C9: IMOBILIÁRIO | D9: 0.32 | E9: 0.11
A10: Moderado-MULTIMERCADO | B10: Moderado | C10: MULTIMERCADO | D10: 0.08 | E10: 0.105
A11: Moderado-AÇÕES BR | B11: Moderado | C11: AÇÕES BR | D11: 0.1 | E11: 0.12
A12: Moderado-INTERNACIONAL | B12: Moderado | C12: INTERNACIONAL | D12: 0.1 | E12: 0.115
A13: Moderado-CRIPTOMOEDAS | B13: Moderado | C13: CRIPTOMOEDAS | D13: 0.05 | E13: 0.18
A14: Agressivo-RENDA FIXA | B14: Agressivo | C14: RENDA FIXA | D14: 0.1 | E14: 0.1
A15: Agressivo-IMOBILIÁRIO | B15: Agressivo | C15: IMOBILIÁRIO | D15: 0.2 | E15: 0.11
A16: Agressivo-MULTIMERCADO | B16: Agressivo | C16: MULTIMERCADO | D16: 0.05 | E16: 0.105
... A19: Agressivo-CRIPTOMOEDAS | B19: Agressivo | C19: CRIPTOMOEDAS | D19: 0.1 | E19: 0.18
